{"success": true, "server": {"name": "Demo Server", "slug": "demo"}, "player": {"uuid": "550e8400-e29b-41d4-a716-446655440009", "player_name": "RedstoneRaven"}, "summary": {"production_type": "ALL", "game_mode": "ALL", "total_amount": 5700, "total_actions": 3989, "unique_items": 6, "unique_recipes": 13, "worlds": 3}, "top_items": [{"output_material": "OAK_PLANKS", "display_name": "Oak Planks", "total_amount": 315, "total_actions": 110, "percent": 5.542466304304838, "rank": 1}, {"output_material": "CRAFTING_TABLE", "display_name": "Crafting Table", "total_amount": 211, "total_actions": 74, "percent": 3.7178465216423184, "rank": 2}, {"output_material": "FURNACE", "display_name": "Furnace", "total_amount": 190, "total_actions": 66, "percent": 3.33989596138472, "rank": 3}, {"output_material": "GOLDEN_APPLE", "display_name": "Golden Apple", "total_amount": 123, "total_actions": 43, "percent": 2.1739997210649404, "rank": 4}, {"output_material": "TORCH", "display_name": "Torch", "total_amount": 159, "total_actions": 55, "percent": 2.798412005764681, "rank": 5}, {"output_material": "FURNACE", "display_name": "Furnace", "total_amount": 371, "total_actions": 129, "percent": 6.511009735316035, "rank": 6}, {"output_material": "IRON_INGOT", "display_name": "Iron Ingot", "total_amount": 302, "total_actions": 105, "percent": 5.306747331436588, "rank": 7}, {"output_material": "TORCH", "display_name": "Torch", "total_amount": 395, "total_actions": 138, "percent": 6.9417355398515195, "rank": 8}], "type_distribution": [{"name": "CRAFTING", "display_name": "Crafting", "total": 3135, "percent": 55.00000000000001}, {"name": "SMELTING", "display_name": "Smelting", "total": 1425, "percent": 25.0}, {"name": "SMITHING", "display_name": "Smithing", "total": 570, "percent": 10.0}, {"name": "STONECUTTING", "display_name": "Stonecutting", "total": 570, "percent": 10.0}], "station_distribution": [{"name": "CRAFTING_TABLE", "display_name": "Crafting Table", "total": 2565, "percent": 45.0}, {"name": "FURNACE", "display_name": "Furnace", "total": 1425, "percent": 25.0}, {"name": "SMITHING_TABLE", "display_name": "Smithing Table", "total": 570, "percent": 10.0}, {"name": "STONECUTTER", "display_name": "Stonecutter", "total": 570, "percent": 10.0}, {"name": "PLAYER_INVENTORY", "display_name": "Player Inventory", "total": 570, "percent": 10.0}], "world_distribution": [{"world_name": "world", "display_name": "Overworld", "total": 3705, "percent": 65.0}, {"world_name": "world_nether", "display_name": "Nether", "total": 1425, "percent": 25.0}, {"world_name": "world_the_end", "display_name": "The End", "total": 570, "percent": 10.0}], "game_mode_distribution": [{"display_name": "Survival", "total": 5472, "percent": 96.0}, {"display_name": "Creative", "total": 228, "percent": 4.0}], "fun_facts": ["5.7K items produced.", "4K actions."], "assets": {"minecraft_assets_enabled": false, "icon_mode": "emoji"}}