{"success": true, "server": {"name": "Demo Server", "slug": "demo"}, "player": {"uuid": "550e8400-e29b-41d4-a716-446655440015", "player_name": "LavaLilly"}, "summary": {"production_type": "ALL", "game_mode": "ALL", "total_amount": 2700, "total_actions": 1889, "unique_items": 13, "unique_recipes": 8, "worlds": 1}, "top_items": [{"output_material": "GOLDEN_APPLE", "display_name": "Golden Apple", "total_amount": 120, "total_actions": 42, "percent": 4.468846522379483, "rank": 1}, {"output_material": "OAK_PLANKS", "display_name": "Oak Planks", "total_amount": 133, "total_actions": 46, "percent": 4.937919318245268, "rank": 2}, {"output_material": "FURNACE", "display_name": "Furnace", "total_amount": 158, "total_actions": 55, "percent": 5.853374678077403, "rank": 3}, {"output_material": "OAK_PLANKS", "display_name": "Oak Planks", "total_amount": 73, "total_actions": 25, "percent": 2.7208939262372334, "rank": 4}, {"output_material": "STICK", "display_name": "Stick", "total_amount": 47, "total_actions": 16, "percent": 1.760928012680833, "rank": 5}, {"output_material": "STICK", "display_name": "Stick", "total_amount": 164, "total_actions": 57, "percent": 6.108671536315805, "rank": 6}, {"output_material": "FURNACE", "display_name": "Furnace", "total_amount": 67, "total_actions": 23, "percent": 2.5123058467748205, "rank": 7}, {"output_material": "FURNACE", "display_name": "Furnace", "total_amount": 71, "total_actions": 25, "percent": 2.6513026889201274, "rank": 8}], "type_distribution": [{"name": "CRAFTING", "display_name": "Crafting", "total": 1485, "percent": 55.00000000000001}, {"name": "SMELTING", "display_name": "Smelting", "total": 675, "percent": 25.0}, {"name": "SMITHING", "display_name": "Smithing", "total": 270, "percent": 10.0}, {"name": "STONECUTTING", "display_name": "Stonecutting", "total": 270, "percent": 10.0}], "station_distribution": [{"name": "CRAFTING_TABLE", "display_name": "Crafting Table", "total": 1215, "percent": 45.0}, {"name": "FURNACE", "display_name": "Furnace", "total": 675, "percent": 25.0}, {"name": "SMITHING_TABLE", "display_name": "Smithing Table", "total": 270, "percent": 10.0}, {"name": "STONECUTTER", "display_name": "Stonecutter", "total": 270, "percent": 10.0}, {"name": "PLAYER_INVENTORY", "display_name": "Player Inventory", "total": 270, "percent": 10.0}], "world_distribution": [{"world_name": "world", "display_name": "Overworld", "total": 1755, "percent": 65.0}, {"world_name": "world_nether", "display_name": "Nether", "total": 675, "percent": 25.0}, {"world_name": "world_the_end", "display_name": "The End", "total": 270, "percent": 10.0}], "game_mode_distribution": [{"display_name": "Survival", "total": 2592, "percent": 96.0}, {"display_name": "Creative", "total": 108, "percent": 4.0}], "fun_facts": ["2.7K items produced.", "1.9K actions."], "assets": {"minecraft_assets_enabled": false, "icon_mode": "emoji"}}