{"success": true, "server": {"name": "Demo Server", "slug": "demo", "mode": "SURVIVAL"}, "player": {"uuid": "550e8400-e29b-41d4-a716-446655440007", "player_name": "NetherKnight_42"}, "summary": {"mined": 17049, "placed": 7158, "total": 24207, "players": 1, "block_types": 22}, "top_blocks": [{"material": "BIRCH_LOG", "display_name": "Birch Log", "category": "Nature", "mined": 366, "placed": 154, "total": 520, "percent": 2.1520659956119417}, {"material": "OAK_PLANKS", "display_name": "Oak Planks", "category": "Building", "mined": 116, "placed": 48, "total": 165, "percent": 0.6829372067985283}, {"material": "CHEST", "display_name": "Chest", "category": "Tech", "mined": 228, "placed": 95, "total": 324, "percent": 1.339327962316914}, {"material": "GOLD_ORE", "display_name": "Gold Ore", "category": "Ores", "mined": 155, "placed": 65, "total": 220, "percent": 0.9117080513961945}, {"material": "OAK_LOG", "display_name": "Oak Log", "category": "Nature", "mined": 187, "placed": 78, "total": 265, "percent": 1.09837341999976}, {"material": "DEEPSLATE", "display_name": "Deepslate", "category": "Building", "mined": 537, "placed": 225, "total": 763, "percent": 3.153957548674895}, {"material": "OBSIDIAN", "display_name": "Obsidian", "category": "Other", "mined": 354, "placed": 148, "total": 502, "percent": 2.0774421747583394}, {"material": "STONE_BRICKS", "display_name": "Stone Bricks", "category": "Building", "mined": 407, "placed": 171, "total": 579, "percent": 2.392263166474266}, {"material": "SPRUCE_PLANKS", "display_name": "Spruce Planks", "category": "Building", "mined": 495, "placed": 208, "total": 703, "percent": 2.9065042483133823}, {"material": "NETHERRACK", "display_name": "Netherrack", "category": "Nether", "mined": 491, "placed": 206, "total": 698, "percent": 2.8845387329056105}, {"material": "COPPER_ORE", "display_name": "Copper Ore", "category": "Ores", "mined": 591, "placed": 248, "total": 839, "percent": 3.468210847284601}, {"material": "GLASS", "display_name": "Glass", "category": "Building", "mined": 485, "placed": 203, "total": 688, "percent": 2.845747300536275}], "world_distribution": [{"world_name": "world", "display_name": "Overworld", "mined": 11081, "placed": 4652, "total": 15734, "percent": 65.0}, {"world_name": "world_nether", "display_name": "Nether", "mined": 4262, "placed": 1789, "total": 6051, "percent": 25.0}, {"world_name": "world_the_end", "display_name": "The End", "mined": 1704, "placed": 715, "total": 2420, "percent": 10.0}], "material_categories": [{"name": "Ores", "mined": 1635, "placed": 343, "total": 1741, "percent": 7.2}, {"name": "Nature", "mined": 1635, "placed": 343, "total": 1741, "percent": 7.2}, {"name": "Building", "mined": 1635, "placed": 343, "total": 1741, "percent": 7.2}, {"name": "Nether", "mined": 1635, "placed": 343, "total": 1741, "percent": 7.2}, {"name": "Tech", "mined": 1635, "placed": 343, "total": 1741, "percent": 7.2}, {"name": "Other", "mined": 1635, "placed": 343, "total": 1741, "percent": 7.2}], "trend": [{"date": "2026-06-01", "mined": 438, "placed": 184}, {"date": "2026-06-02", "mined": 421, "placed": 177}, {"date": "2026-06-03", "mined": 543, "placed": 228}, {"date": "2026-06-04", "mined": 426, "placed": 179}, {"date": "2026-06-05", "mined": 394, "placed": 165}, {"date": "2026-06-06", "mined": 335, "placed": 140}, {"date": "2026-06-07", "mined": 374, "placed": 157}, {"date": "2026-06-08", "mined": 346, "placed": 145}, {"date": "2026-06-09", "mined": 538, "placed": 226}, {"date": "2026-06-10", "mined": 505, "placed": 212}, {"date": "2026-06-11", "mined": 300, "placed": 126}, {"date": "2026-06-12", "mined": 565, "placed": 237}, {"date": "2026-06-13", "mined": 434, "placed": 182}, {"date": "2026-06-14", "mined": 502, "placed": 210}, {"date": "2026-06-15", "mined": 568, "placed": 238}, {"date": "2026-06-16", "mined": 560, "placed": 235}, {"date": "2026-06-17", "mined": 312, "placed": 131}, {"date": "2026-06-18", "mined": 470, "placed": 197}, {"date": "2026-06-19", "mined": 359, "placed": 151}, {"date": "2026-06-20", "mined": 516, "placed": 216}, {"date": "2026-06-21", "mined": 544, "placed": 228}, {"date": "2026-06-22", "mined": 300, "placed": 125}, {"date": "2026-06-23", "mined": 567, "placed": 238}, {"date": "2026-06-24", "mined": 346, "placed": 145}, {"date": "2026-06-25", "mined": 524, "placed": 220}, {"date": "2026-06-26", "mined": 510, "placed": 214}, {"date": "2026-06-27", "mined": 384, "placed": 161}, {"date": "2026-06-28", "mined": 522, "placed": 219}, {"date": "2026-06-29", "mined": 524, "placed": 220}, {"date": "2026-06-30", "mined": 334, "placed": 140}], "fun_facts": ["17K blocks mined.", "7.2K blocks placed.", "Total: 24.2K blocks."], "assets": {"minecraft_assets_enabled": false, "icon_mode": "emoji"}, "rankings": {"mined_rank": 10, "placed_rank": 6, "total_rank": 13}}